swh/dataset/__init__.py
swh/dataset/athena.py
swh/dataset/cli.py
swh/dataset/exporter.py
swh/dataset/journalprocessor.py
swh/dataset/luigi.py
swh/dataset/py.typed
swh/dataset/relational.py
swh/dataset/utils.py
swh/dataset/exporters/__init__.py
swh/dataset/exporters/edges.py
swh/dataset/exporters/orc.py
swh/dataset/test/test_edges.py
swh/dataset/test/test_journal_processor.py
swh/dataset/test/test_orc.py
swh/dataset/test/test_utils.py
swh.dataset-1.7.1.dist-info/AUTHORS
swh.dataset-1.7.1.dist-info/LICENSE
swh.dataset-1.7.1.dist-info/METADATA
swh.dataset-1.7.1.dist-info/WHEEL
swh.dataset-1.7.1.dist-info/entry_points.txt
swh.dataset-1.7.1.dist-info/top_level.txt
swh.dataset-1.7.1.dist-info/RECORD
